casimac/__init__.py
casimac/casimac.py
casimac-1.2.4.dist-info/LICENSE
casimac-1.2.4.dist-info/METADATA
casimac-1.2.4.dist-info/WHEEL
casimac-1.2.4.dist-info/top_level.txt
casimac-1.2.4.dist-info/RECORD
