Metadata-Version: 2.1
Name: casimac
Version: 1.2.4
Summary: Supervised multi-class/single-label classification with gradients
Home-page: https://github.com/RaoulHeese/casimac
Download-URL: https://github.com/RaoulHeese/casimac
Author: Raoul Heese
Author-email: raoul.heese@gmail.com
Maintainer: Raoul Heese
Maintainer-email: raoul.heese@gmail.com
License: MIT
Project-URL: Source Code, https://github.com/RaoulHeese/casimac
License-File: LICENSE
Requires-Dist: numpy
Requires-Dist: scikit-learn
Requires-Dist: scipy
